README.md
setup.py
texar/__init__.py
texar.egg-info/PKG-INFO
texar.egg-info/SOURCES.txt
texar.egg-info/dependency_links.txt
texar.egg-info/requires.txt
texar.egg-info/top_level.txt
texar/../bin/utils/multi-bleu.perl
texar/tf/__init__.py
texar/tf/context.py
texar/tf/context_test.py
texar/tf/hyperparams.py
texar/tf/hyperparams_test.py
texar/tf/module_base.py
texar/tf/version.py
texar/tf/agents/__init__.py
texar/tf/agents/ac_agent.py
texar/tf/agents/agent_base.py
texar/tf/agents/agent_gym_utils.py
texar/tf/agents/agent_utils.py
texar/tf/agents/agent_utils_test.py
texar/tf/agents/dqn_agent.py
texar/tf/agents/episodic_agent_base.py
texar/tf/agents/pg_agent.py
texar/tf/agents/seq_agent_base.py
texar/tf/agents/seq_pg_agent.py
texar/tf/agents/seq_pg_agent_test.py
texar/tf/core/__init__.py
texar/tf/core/explorations.py
texar/tf/core/layers.py
texar/tf/core/layers_test.py
texar/tf/core/optimization.py
texar/tf/core/optimization_test.py
texar/tf/core/replay_memories.py
texar/tf/custom/__init__.py
texar/tf/data/__init__.py
texar/tf/data/data_decoders.py
texar/tf/data/data_utils.py
texar/tf/data/data_utils_test.py
texar/tf/data/embedding.py
texar/tf/data/embedding_test.py
texar/tf/data/vocabulary.py
texar/tf/data/vocabulary_test.py
texar/tf/data/data/__init__.py
texar/tf/data/data/data_base.py
texar/tf/data/data/data_iterators.py
texar/tf/data/data/data_iterators_test.py
texar/tf/data/data/dataset_utils.py
texar/tf/data/data/dataset_utils_test.py
texar/tf/data/data/mono_text_data.py
texar/tf/data/data/mono_text_data_test.py
texar/tf/data/data/multi_aligned_data.py
texar/tf/data/data/multi_aligned_data_test.py
texar/tf/data/data/paired_text_data.py
texar/tf/data/data/paired_text_data_test.py
texar/tf/data/data/scalar_data.py
texar/tf/data/data/scalar_data_test.py
texar/tf/data/data/text_data_base.py
texar/tf/data/data/tfrecord_data.py
texar/tf/data/data/tfrecord_data_test.py
texar/tf/data/tokenizers/__init__.py
texar/tf/data/tokenizers/bert_tokenizer.py
texar/tf/data/tokenizers/bert_tokenizer_test.py
texar/tf/data/tokenizers/bert_tokenizer_utils.py
texar/tf/data/tokenizers/bert_tokenizer_utils_test.py
