Metadata-Version: 2.1
Name: texar
Version: 0.2.4
Summary: Toolkit for Machine Learning and Text Generation
Home-page: https://github.com/asyml/texar
License: Apache License Version 2.0
Platform: any
Classifier: Intended Audience :: Developers
Classifier: Intended Audience :: Education
Classifier: Intended Audience :: Science/Research
Classifier: Operating System :: OS Independent
Classifier: Programming Language :: Python
Classifier: Programming Language :: Python :: 3.6
Classifier: Programming Language :: Python :: 3.7
Provides-Extra: tensorflow-gpu
Provides-Extra: tensorflow-cpu
